pipeline_penguin/__init__.py
pipeline_penguin/exceptions.py
pipeline_penguin/__pycache__/__init__.cpython-39.pyc
pipeline_penguin/__pycache__/exceptions.cpython-39.pyc
pipeline_penguin/connector/__init__.py
pipeline_penguin/connector/connector_manager.py
pipeline_penguin/connector/__pycache__/__init__.cpython-39.pyc
pipeline_penguin/connector/__pycache__/connector_manager.cpython-39.pyc
pipeline_penguin/connector/sql/__init__.py
pipeline_penguin/connector/sql/bigquery.py
pipeline_penguin/connector/sql/__pycache__/__init__.cpython-39.pyc
pipeline_penguin/connector/sql/__pycache__/bigquery.cpython-39.pyc
pipeline_penguin/core/__init__.py
pipeline_penguin/core/__pycache__/__init__.cpython-39.pyc
pipeline_penguin/core/connector/__init__.py
pipeline_penguin/core/connector/connector.py
pipeline_penguin/core/connector/sql.py
pipeline_penguin/core/connector/__pycache__/__init__.cpython-39.pyc
pipeline_penguin/core/connector/__pycache__/connector.cpython-39.pyc
pipeline_penguin/core/connector/__pycache__/sql.cpython-39.pyc
pipeline_penguin/core/data_node/__init__.py
pipeline_penguin/core/data_node/data_node.py
pipeline_penguin/core/data_node/__pycache__/__init__.cpython-39.pyc
pipeline_penguin/core/data_node/__pycache__/data_node.cpython-39.pyc
pipeline_penguin/core/data_premise/__init__.py
pipeline_penguin/core/data_premise/data_premise.py
pipeline_penguin/core/data_premise/sql.py
pipeline_penguin/core/data_premise/__pycache__/__init__.cpython-39.pyc
pipeline_penguin/core/data_premise/__pycache__/data_premise.cpython-39.pyc
pipeline_penguin/core/data_premise/__pycache__/sql.cpython-39.pyc
pipeline_penguin/core/premise_output/__init__.py
pipeline_penguin/core/premise_output/output_exporter.py
pipeline_penguin/core/premise_output/output_formatter.py
pipeline_penguin/core/premise_output/output_manager.py
pipeline_penguin/core/premise_output/premise_output.py
pipeline_penguin/core/premise_output/__pycache__/__init__.cpython-39.pyc
pipeline_penguin-0.1.3.dist-info/METADATA
pipeline_penguin-0.1.3.dist-info/WHEEL
pipeline_penguin-0.1.3.dist-info/top_level.txt
pipeline_penguin-0.1.3.dist-info/RECORD
