Metadata-Version: 2.1
Name: pipeline-penguin
Version: 0.1.3
Summary: Pipeline Penguin is a versatile python library for data quality.
Home-page: https://github.com/DP6/pipeline-penguin
Author: DP6
Author-email: bruno.munhoz@dp6.com.br
License: UNKNOWN
Project-URL: Bug Tracker, https://github.com/DP6/pipeline-penguin/issues
Platform: UNKNOWN
Classifier: Programming Language :: Python :: 3
Classifier: Operating System :: OS Independent
Requires-Python: >=3.9
Requires-Dist: pandas
Requires-Dist: pandas-gbq
